[
  {
    "ContainingType": "TaskManagement.API.Controllers.AuthController",
    "Method": "Login",
    "RelativePath": "api/auth/login",
    "HttpMethod": "POST",
    "IsController": true,
    "Order": 0,
    "Parameters": [
      {
        "Name": "request",
        "Type": "TaskManagement.Application.DTOs.LoginRequest",
        "IsRequired": true
      }
    ],
    "ReturnTypes": [
      {
        "Type": "TaskManagement.Application.DTOs.ApiResponse\u00601[[TaskManagement.Application.DTOs.AuthResponse, TaskManagement.Application, Version=1.0.0.0, Culture=neutral, PublicKeyToken=null]]",
        "MediaTypes": [
          "application/json"
        ],
        "StatusCode": 200
      },
      {
        "Type": "TaskManagement.Application.DTOs.ApiResponse",
        "MediaTypes": [
          "application/json"
        ],
        "StatusCode": 401
      }
    ]
  },
  {
    "ContainingType": "TaskManagement.API.Controllers.AuthController",
    "Method": "RefreshToken",
    "RelativePath": "api/auth/refresh-token",
    "HttpMethod": "POST",
    "IsController": true,
    "Order": 0,
    "Parameters": [
      {
        "Name": "request",
        "Type": "TaskManagement.Application.DTOs.RefreshTokenRequest",
        "IsRequired": true
      }
    ],
    "ReturnTypes": [
      {
        "Type": "TaskManagement.Application.DTOs.ApiResponse\u00601[[TaskManagement.Application.DTOs.AuthResponse, TaskManagement.Application, Version=1.0.0.0, Culture=neutral, PublicKeyToken=null]]",
        "MediaTypes": [
          "application/json"
        ],
        "StatusCode": 200
      }
    ]
  },
  {
    "ContainingType": "TaskManagement.API.Controllers.AuthController",
    "Method": "Register",
    "RelativePath": "api/auth/register",
    "HttpMethod": "POST",
    "IsController": true,
    "Order": 0,
    "Parameters": [
      {
        "Name": "request",
        "Type": "TaskManagement.Application.DTOs.RegisterRequest",
        "IsRequired": true
      }
    ],
    "ReturnTypes": [
      {
        "Type": "TaskManagement.Application.DTOs.ApiResponse\u00601[[TaskManagement.Application.DTOs.AuthResponse, TaskManagement.Application, Version=1.0.0.0, Culture=neutral, PublicKeyToken=null]]",
        "MediaTypes": [
          "application/json"
        ],
        "StatusCode": 201
      },
      {
        "Type": "TaskManagement.Application.DTOs.ApiResponse",
        "MediaTypes": [
          "application/json"
        ],
        "StatusCode": 409
      }
    ]
  },
  {
    "ContainingType": "TaskManagement.API.Controllers.AuthController",
    "Method": "RevokeToken",
    "RelativePath": "api/auth/revoke-token",
    "HttpMethod": "POST",
    "IsController": true,
    "Order": 0,
    "Parameters": [
      {
        "Name": "request",
        "Type": "TaskManagement.Application.DTOs.RefreshTokenRequest",
        "IsRequired": true
      }
    ],
    "ReturnTypes": [
      {
        "Type": "TaskManagement.Application.DTOs.ApiResponse",
        "MediaTypes": [
          "application/json"
        ],
        "StatusCode": 200
      }
    ]
  },
  {
    "ContainingType": "TaskManagement.API.Controllers.TasksController",
    "Method": "Create",
    "RelativePath": "api/tasks",
    "HttpMethod": "POST",
    "IsController": true,
    "Order": 0,
    "Parameters": [
      {
        "Name": "request",
        "Type": "TaskManagement.Application.DTOs.CreateTaskRequest",
        "IsRequired": true
      }
    ],
    "ReturnTypes": [
      {
        "Type": "TaskManagement.Application.DTOs.ApiResponse\u00601[[TaskManagement.Application.DTOs.TaskDto, TaskManagement.Application, Version=1.0.0.0, Culture=neutral, PublicKeyToken=null]]",
        "MediaTypes": [
          "application/json"
        ],
        "StatusCode": 201
      },
      {
        "Type": "TaskManagement.Application.DTOs.ApiResponse",
        "MediaTypes": [
          "application/json"
        ],
        "StatusCode": 409
      }
    ]
  },
  {
    "ContainingType": "TaskManagement.API.Controllers.TasksController",
    "Method": "GetAll",
    "RelativePath": "api/tasks",
    "HttpMethod": "GET",
    "IsController": true,
    "Order": 0,
    "Parameters": [],
    "ReturnTypes": [
      {
        "Type": "TaskManagement.Application.DTOs.ApiResponse\u00601[[System.Collections.Generic.IReadOnlyList\u00601[[TaskManagement.Application.DTOs.TaskDto, TaskManagement.Application, Version=1.0.0.0, Culture=neutral, PublicKeyToken=null]], System.Private.CoreLib, Version=8.0.0.0, Culture=neutral, PublicKeyToken=7cec85d7bea7798e]]",
        "MediaTypes": [
          "application/json"
        ],
        "StatusCode": 200
      }
    ]
  },
  {
    "ContainingType": "TaskManagement.API.Controllers.TasksController",
    "Method": "GetById",
    "RelativePath": "api/tasks/{id}",
    "HttpMethod": "GET",
    "IsController": true,
    "Order": 0,
    "Parameters": [
      {
        "Name": "id",
        "Type": "System.Guid",
        "IsRequired": true
      }
    ],
    "ReturnTypes": [
      {
        "Type": "TaskManagement.Application.DTOs.ApiResponse\u00601[[TaskManagement.Application.DTOs.TaskDto, TaskManagement.Application, Version=1.0.0.0, Culture=neutral, PublicKeyToken=null]]",
        "MediaTypes": [
          "application/json"
        ],
        "StatusCode": 200
      },
      {
        "Type": "TaskManagement.Application.DTOs.ApiResponse",
        "MediaTypes": [
          "application/json"
        ],
        "StatusCode": 404
      },
      {
        "Type": "TaskManagement.Application.DTOs.ApiResponse",
        "MediaTypes": [
          "application/json"
        ],
        "StatusCode": 403
      }
    ]
  },
  {
    "ContainingType": "TaskManagement.API.Controllers.TasksController",
    "Method": "UpdateStatus",
    "RelativePath": "api/tasks/{id}/status",
    "HttpMethod": "PATCH",
    "IsController": true,
    "Order": 0,
    "Parameters": [
      {
        "Name": "id",
        "Type": "System.Guid",
        "IsRequired": true
      },
      {
        "Name": "request",
        "Type": "TaskManagement.Application.DTOs.UpdateTaskStatusRequest",
        "IsRequired": true
      }
    ],
    "ReturnTypes": [
      {
        "Type": "TaskManagement.Application.DTOs.ApiResponse\u00601[[TaskManagement.Application.DTOs.TaskDto, TaskManagement.Application, Version=1.0.0.0, Culture=neutral, PublicKeyToken=null]]",
        "MediaTypes": [
          "application/json"
        ],
        "StatusCode": 200
      },
      {
        "Type": "TaskManagement.Application.DTOs.ApiResponse",
        "MediaTypes": [
          "application/json"
        ],
        "StatusCode": 404
      },
      {
        "Type": "TaskManagement.Application.DTOs.ApiResponse",
        "MediaTypes": [
          "application/json"
        ],
        "StatusCode": 403
      }
    ]
  },
  {
    "ContainingType": "TaskManagement.API.Controllers.UsersController",
    "Method": "GetAll",
    "RelativePath": "api/users",
    "HttpMethod": "GET",
    "IsController": true,
    "Order": 0,
    "Parameters": [],
    "ReturnTypes": [
      {
        "Type": "TaskManagement.Application.DTOs.ApiResponse\u00601[[System.Collections.Generic.IReadOnlyList\u00601[[TaskManagement.Application.DTOs.UserDto, TaskManagement.Application, Version=1.0.0.0, Culture=neutral, PublicKeyToken=null]], System.Private.CoreLib, Version=8.0.0.0, Culture=neutral, PublicKeyToken=7cec85d7bea7798e]]",
        "MediaTypes": [
          "application/json"
        ],
        "StatusCode": 200
      }
    ]
  },
  {
    "ContainingType": "TaskManagement.API.Controllers.UsersController",
    "Method": "Create",
    "RelativePath": "api/users",
    "HttpMethod": "POST",
    "IsController": true,
    "Order": 0,
    "Parameters": [
      {
        "Name": "request",
        "Type": "TaskManagement.Application.DTOs.CreateUserRequest",
        "IsRequired": true
      }
    ],
    "ReturnTypes": [
      {
        "Type": "TaskManagement.Application.DTOs.ApiResponse\u00601[[TaskManagement.Application.DTOs.UserDto, TaskManagement.Application, Version=1.0.0.0, Culture=neutral, PublicKeyToken=null]]",
        "MediaTypes": [
          "application/json"
        ],
        "StatusCode": 201
      },
      {
        "Type": "TaskManagement.Application.DTOs.ApiResponse",
        "MediaTypes": [
          "application/json"
        ],
        "StatusCode": 409
      }
    ]
  },
  {
    "ContainingType": "TaskManagement.API.Controllers.UsersController",
    "Method": "Delete",
    "RelativePath": "api/users/{id}",
    "HttpMethod": "DELETE",
    "IsController": true,
    "Order": 0,
    "Parameters": [
      {
        "Name": "id",
        "Type": "System.Guid",
        "IsRequired": true
      }
    ],
    "ReturnTypes": [
      {
        "Type": "TaskManagement.Application.DTOs.ApiResponse",
        "MediaTypes": [
          "application/json"
        ],
        "StatusCode": 200
      },
      {
        "Type": "TaskManagement.Application.DTOs.ApiResponse",
        "MediaTypes": [
          "application/json"
        ],
        "StatusCode": 404
      }
    ]
  },
  {
    "ContainingType": "TaskManagement.API.Controllers.UsersController",
    "Method": "GetMe",
    "RelativePath": "api/users/me",
    "HttpMethod": "GET",
    "IsController": true,
    "Order": 0,
    "Parameters": [],
    "ReturnTypes": [
      {
        "Type": "TaskManagement.Application.DTOs.ApiResponse\u00601[[TaskManagement.Application.DTOs.UserDto, TaskManagement.Application, Version=1.0.0.0, Culture=neutral, PublicKeyToken=null]]",
        "MediaTypes": [
          "application/json"
        ],
        "StatusCode": 200
      }
    ]
  }
]